emailo/__init__.py
emailo/console.py
emailo/utils.py
emailo-0.2.0.dist-info/entry_points.txt
emailo-0.2.0.dist-info/LICENSE
emailo-0.2.0.dist-info/WHEEL
emailo-0.2.0.dist-info/METADATA
emailo-0.2.0.dist-info/RECORD
